jupyter_theme_editor/__init__.py
jupyter_theme_editor/_version.py
jupyter_theme_editor/handlers.py
jupyter_theme_editor/templates/template.css
jupyter_theme_editor/tests/__init__.py
jupyter_theme_editor/tests/test_handlers.py
jupyter_theme_editor-0.4.2.data/data/etc/jupyter/jupyter_notebook_config.d/jupyter_theme_editor.json
jupyter_theme_editor-0.4.2.data/data/etc/jupyter/jupyter_server_config.d/jupyter_theme_editor.json
jupyter_theme_editor-0.4.2.data/data/share/jupyter/labextensions/jupyter-theme-editor/package.json
jupyter_theme_editor-0.4.2.data/data/share/jupyter/labextensions/jupyter-theme-editor/schemas/jupyter-theme-editor/package.json.orig
jupyter_theme_editor-0.4.2.data/data/share/jupyter/labextensions/jupyter-theme-editor/schemas/jupyter-theme-editor/plugin.json
jupyter_theme_editor-0.4.2.data/data/share/jupyter/labextensions/jupyter-theme-editor/static/304.caed9225fc88627a1ade.js
jupyter_theme_editor-0.4.2.data/data/share/jupyter/labextensions/jupyter-theme-editor/static/351.9ec43e8031fd2252d01d.js
jupyter_theme_editor-0.4.2.data/data/share/jupyter/labextensions/jupyter-theme-editor/static/535.251e4fef15db43619f3b.js
jupyter_theme_editor-0.4.2.data/data/share/jupyter/labextensions/jupyter-theme-editor/static/747.e721e56eaf04858131e6.js
jupyter_theme_editor-0.4.2.data/data/share/jupyter/labextensions/jupyter-theme-editor/static/807.deac369ec79332e05c33.js
jupyter_theme_editor-0.4.2.data/data/share/jupyter/labextensions/jupyter-theme-editor/static/807.deac369ec79332e05c33.js.LICENSE.txt
jupyter_theme_editor-0.4.2.data/data/share/jupyter/labextensions/jupyter-theme-editor/static/861.7c8ce849384f01571a74.js
jupyter_theme_editor-0.4.2.data/data/share/jupyter/labextensions/jupyter-theme-editor/static/remoteEntry.663b43235d5c441becb5.js
jupyter_theme_editor-0.4.2.data/data/share/jupyter/labextensions/jupyter-theme-editor/static/style.js
jupyter_theme_editor-0.4.2.data/data/share/jupyter/labextensions/jupyter-theme-editor/static/third-party-licenses.json
jupyter_theme_editor-0.4.2.dist-info/METADATA
jupyter_theme_editor-0.4.2.dist-info/WHEEL
jupyter_theme_editor-0.4.2.dist-info/licenses/LICENSE
jupyter_theme_editor-0.4.2.dist-info/RECORD
